paddlespeechserver-0.1.0.dist-info/METADATA
paddlespeechserver-0.1.0.dist-info/WHEEL
paddlespeechserver/__init__.py
paddlespeechserver/hellworld.py
paddlespeechserver-0.1.0.dist-info/RECORD
